sssom/__init__.py
sssom/cli.py
sssom/cliques.py
sssom/cliquesummary.py
sssom/constants.py
sssom/context.py
sssom/inverse_map.yaml
sssom/io.py
sssom/obo.epm.json
sssom/parsers.py
sssom/py.typed
sssom/rdf_internal.py
sssom/rdf_util.py
sssom/sparql_util.py
sssom/sssom_document.py
sssom/util.py
sssom/validators.py
sssom/writers.py
sssom-0.4.18.dist-info/METADATA
sssom-0.4.18.dist-info/WHEEL
sssom-0.4.18.dist-info/entry_points.txt
sssom-0.4.18.dist-info/licenses/LICENSE
sssom-0.4.18.dist-info/RECORD
