Metadata-Version: 2.4
Name: sssom
Version: 0.4.18
Summary: Operations on SSSOM mapping tables
License-Expression: MIT
License-File: LICENSE
Author: Chris Mungall
Author-email: cjmungall@lbl.gov
Requires-Python: >=3.10,<4.0.0
Classifier: Programming Language :: Python :: 3
Classifier: Programming Language :: Python :: 3.10
Classifier: Programming Language :: Python :: 3.11
Classifier: Programming Language :: Python :: 3.12
Classifier: Programming Language :: Python :: 3.13
Classifier: Programming Language :: Python :: 3.14
Provides-Extra: docs
Provides-Extra: networkx
Provides-Extra: pansql
Provides-Extra: rdflib-endpoint
Provides-Extra: scipy
Requires-Dist: click (>=8.1.6)
Requires-Dist: curies (>=0.10.23)
Requires-Dist: deprecation (>=2.1.0)
Requires-Dist: fastapi ; extra == "rdflib-endpoint"
Requires-Dist: httpx ; extra == "rdflib-endpoint"
Requires-Dist: linkml (>1.7.10)
Requires-Dist: linkml-runtime (>=1.7.5)
Requires-Dist: myst-parser (>=0.18.1) ; extra == "docs"
Requires-Dist: networkx (>=3.1) ; extra == "networkx"
Requires-Dist: packaging (>=20.0)
Requires-Dist: pandas (>1.0.3)
Requires-Dist: pansql (>=0.0.1) ; extra == "pansql"
Requires-Dist: pyyaml (>=6.0.1)
Requires-Dist: rdflib (>=7.1.3)
Requires-Dist: rdflib-endpoint ; extra == "rdflib-endpoint"
Requires-Dist: scipy ; extra == "scipy"
Requires-Dist: sparqlwrapper (>=2.0.0)
Requires-Dist: sphinx (>=6.1.3) ; extra == "docs"
Requires-Dist: sphinx-autodoc-typehints (>=1.2.0) ; extra == "docs"
Requires-Dist: sphinx-click (>=4.3.0) ; extra == "docs"
Requires-Dist: sphinx-rtd-theme (>=1.0.0) ; extra == "docs"
Requires-Dist: sssom-schema (==1.1.0a3)
Requires-Dist: uvicorn ; extra == "rdflib-endpoint"
Requires-Dist: validators (>=0.20.0)
